program_synthesis/__init__.py
program_synthesis/algolisp/__init__.py
program_synthesis/algolisp/arguments.py
program_synthesis/algolisp/eval.py
program_synthesis/algolisp/train.py
program_synthesis/algolisp/dataset/__init__.py
program_synthesis/algolisp/dataset/code_base.py
program_synthesis/algolisp/dataset/code_lisp.py
program_synthesis/algolisp/dataset/code_lisp_parser.py
program_synthesis/algolisp/dataset/code_lisp_test.py
program_synthesis/algolisp/dataset/code_trace.py
program_synthesis/algolisp/dataset/code_types.py
program_synthesis/algolisp/dataset/code_types_test.py
program_synthesis/algolisp/dataset/data.py
program_synthesis/algolisp/dataset/data_test.py
program_synthesis/algolisp/dataset/dataset.py
program_synthesis/algolisp/dataset/evaluation.py
program_synthesis/algolisp/dataset/executor.py
program_synthesis/algolisp/models/__init__.py
program_synthesis/algolisp/models/base.py
program_synthesis/algolisp/models/prepare_spec.py
program_synthesis/algolisp/models/seq2code_model.py
program_synthesis/algolisp/models/seq2seq_model.py
program_synthesis/algolisp/tools/__init__.py
program_synthesis/algolisp/tools/bleu.py
program_synthesis/algolisp/tools/bleu_test.py
program_synthesis/algolisp/tools/evaluation.py
program_synthesis/algolisp/tools/timer.py
program_synthesis/common/__init__.py
program_synthesis/common/models/__init__.py
program_synthesis/common/models/beam_search.py
program_synthesis/common/modules/__init__.py
program_synthesis/common/modules/attention.py
program_synthesis/common/modules/decoders.py
program_synthesis/common/modules/layer_norm.py
program_synthesis/common/modules/slicing_joining.py
program_synthesis/common/modules/slicing_joining_test.py
program_synthesis/common/tools/__init__.py
program_synthesis/common/tools/reporter.py
program_synthesis/common/tools/saver.py
program_synthesis/karel/__init__.py
program_synthesis/karel/arguments.py
program_synthesis/karel/eval.py
program_synthesis-0.1.2.dist-info/METADATA
program_synthesis-0.1.2.dist-info/RECORD
program_synthesis-0.1.2.dist-info/WHEEL
program_synthesis-0.1.2.dist-info/top_level.txt
