Metadata-Version: 2.1
Name: program-synthesis
Version: 0.1.2
Summary: NEAR Program Synthesis: models, tools, and datasets for program synthesis tasks
Home-page: UNKNOWN
Author: NEAR Inc and Contributors
Author-email: contact@near.ai
License: UNKNOWN
Project-URL: Source, https://github.com/nearai/program_synthesis
Platform: UNKNOWN
Requires-Python: ~=3.5
Requires-Dist: boto3 (~=1.7.10)
Requires-Dist: cached-property (~=1.4)
Requires-Dist: ipython (~=5.5.0)
Requires-Dist: gym (~=0.10.5)
Requires-Dist: numpy (~=1.13.0)
Requires-Dist: torchfold (~=0.1.0)
Requires-Dist: ply (~=3.8)
Requires-Dist: pylru (~=1.0.9)
Requires-Dist: pyparsing (~=2.2.0)
Requires-Dist: pytest (~=3.5)
Requires-Dist: pytest-timeout (~=1.2)
Requires-Dist: pytest-xdist (~=1.22)
Requires-Dist: python-Levenshtein (~=0.12.0)
Requires-Dist: prompt-toolkit (~=1.0.15)
Requires-Dist: tensorflow (~=1.5.0)
Requires-Dist: tqdm (~=4.23.4)
